tree_sitter_plsql_ifs.cpython-312-x86_64-linux-gnu.so
tree_sitter/parser.h
tree_sitter_plsql_ifs-0.1.0.dist-info/METADATA
tree_sitter_plsql_ifs-0.1.0.dist-info/WHEEL
tree_sitter_plsql_ifs-0.1.0.dist-info/top_level.txt
tree_sitter_plsql_ifs-0.1.0.dist-info/RECORD
